[{"Rank": "1", "Player": "Antoine Davis, Detroit Mercy (Horizon)", "Cl": "Sr.", "Ht": "6-1", "Pos": "G", "G": "33", "FGM": "303", "3FG": "159", "FT": "165", "PTS": "930", "PPG": "28.2"}, {"Rank": "2", "Player": "Jordan Dingle, Penn (Ivy League)", "Cl": "Jr.", "Ht": "6-3", "Pos": "G", "G": "27", "FGM": "209", "3FG": "76", "FT": "143", "PTS": "637", "PPG": "23.6"}, {"Rank": "3", "Player": "Jordan Walker, UAB (C-USA)", "Cl": "Sr.", "Ht": "5-11", "Pos": "G", "G": "25", "FGM": "187", "3FG": "109", "FT": "96", "PTS": "579", "PPG": "23.2"}, {"Rank": "4", "Player": "Elijah Pepper, UC Davis (Big West)", "Cl": "Jr.", "Ht": "6-4", "Pos": "G", "G": "30", "FGM": "223", "3FG": "68", "FT": "161", "PTS": "675", "PPG": "22.5"}, {"Rank": "5", "Player": "Darius McGhee, Liberty (ASUN)", "Cl": "Sr.", "Ht": "5-9", "Pos": "G", "G": "34", "FGM": "255", "3FG": "153", "FT": "101", "PTS": "764", "PPG": "22.5"}, {"Rank": "6", "Player": "Taevion Kinsey, Marshall (Sun Belt)", "Cl": "Sr.", "Ht": "6-5", "Pos": "G", "G": "32", "FGM": "271", "3FG": "19", "FT": "145", "PTS": "706", "PPG": "22.1"}, {"Rank": "7", "Player": "Max Abmas, Oral Roberts (Summit League)", "Cl": "Sr.", "Ht": "6-0", "Pos": "G", "G": "31", "FGM": "216", "3FG": "111", "FT": "139", "PTS": "682", "PPG": "22.0"}, {"Rank": "8", "Player": "Zach Edey, Purdue (Big Ten)", "Cl": "Jr.", "Ht": "7-4", "Pos": "C", "G": "30", "FGM": "253", "3FG": "0", "FT": "152", "PTS": "658", "PPG": "21.9"}, {"Rank": "9", "Player": "Josh Cohen, Saint Francis (PA) (NEC)", "Cl": "Jr.", "Ht": "6-10", "Pos": "F", "G": "31", "FGM": "257", "3FG": "0", "FT": "162", "PTS": "676", "PPG": "21.8"}, {"Rank": "10", "Player": "James Bishop, George Washington (Atlantic 10)", "Cl": "Sr.", "Ht": "6-2", "Pos": "G", "G": "31", "FGM": "232", "3FG": "62", "FT": "140", "PTS": "666", "PPG": "21.5"}, {"Rank": "11", "Player": "Kendric Davis, Memphis (AAC)", "Cl": "Sr.", "Ht": "5-11", "Pos": "G", "G": "30", "FGM": "197", "3FG": "51", "FT": "199", "PTS": "644", "PPG": "21.5"}, {"Rank": "12", "Player": "Xavier Castaneda, Akron (MAC)", "Cl": "Sr.", "Ht": "6-1", "Pos": "G", "G": "29", "FGM": "162", "3FG": "102", "FT": "196", "PTS": "622", "PPG": "21.4"}, {"Rank": "13", "Player": "Cam Shelton, LMU (CA) (WCC)", "Cl": "Sr.", "Ht": "6-2", "Pos": "G", "G": "31", "FGM": "243", "3FG": "55", "FT": "123", "PTS": "664", "PPG": "21.4"}, {"Rank": "14", "Player": "Drew Pember, UNC Asheville (Big South)", "Cl": "Sr.", "Ht": "6-10", "Pos": "F", "G": "34", "FGM": "201", "3FG": "56", "FT": "262", "PTS": "720", "PPG": "21.2"}, {"Rank": "15", "Player": "Drew Timme, Gonzaga (WCC)", "Cl": "Sr.", "Ht": "6-10", "Pos": "F", "G": "31", "FGM": "259", "3FG": "2", "FT": "134", "PTS": "654", "PPG": "21.1"}, {"Rank": "16", "Player": "Sam Sessoms, Coppin St. (MEAC)", "Cl": "Sr.", "Ht": "6-0", "Pos": "G", "G": "31", "FGM": "235", "3FG": "56", "FT": "117", "PTS": "643", "PPG": "20.7"}, {"Rank": "17", "Player": "Jameer Nelson Jr., Delaware (CAA)", "Cl": "Jr.", "Ht": "6-1", "Pos": "G", "G": "29", "FGM": "194", "3FG": "50", "FT": "159", "PTS": "597", "PPG": "20.6"}, {"Rank": "18", "Player": "Justin Johnson, UTRGV (WAC)", "Cl": "Sr.", "Ht": "6-6", "Pos": "G", "G": "30", "FGM": "203", "3FG": "28", "FT": "183", "PTS": "617", "PPG": "20.6"}, {"Rank": "19", "Player": "Trayce Jackson-Davis, Indiana (Big Ten)", "Cl": "Sr.", "Ht": "6-9", "Pos": "F", "G": "28", "FGM": "226", "3FG": "0", "FT": "123", "PTS": "575", "PPG": "20.5"}, {"Rank": "20", "Player": "Kris Murray, Iowa (Big Ten)", "Cl": "Jr.", "Ht": "6-8", "Pos": "F", "G": "27", "FGM": "205", "3FG": "61", "FT": "83", "PTS": "554", "PPG": "20.5"}, {"Rank": "21", "Player": "Jalen Cook, Tulane (AAC)", "Cl": "So.", "Ht": "6-0", "Pos": "G", "G": "24", "FGM": "173", "3FG": "54", "FT": "90", "PTS": "490", "PPG": "20.4"}, {"Rank": "22", "Player": "Aaron Estrada, Hofstra (CAA)", "Cl": "Sr.", "Ht": "6-3", "Pos": "G", "G": "28", "FGM": "218", "3FG": "62", "FT": "72", "PTS": "570", "PPG": "20.4"}, {"Rank": "23", "Player": "Trey Calvin, Wright St. (Horizon)", "Cl": "Sr.", "Ht": "6-0", "Pos": "G", "G": "32", "FGM": "250", "3FG": "53", "FT": "98", "PTS": "651", "PPG": "20.3"}, {"Rank": "24", "Player": "Dalton Knecht, Northern Colo. (Big Sky)", "Cl": "Sr.", "Ht": "6-6", "Pos": "G", "G": "32", "FGM": "234", "3FG": "77", "FT": "101", "PTS": "646", "PPG": "20.2"}, {"Rank": "25", "Player": "Andrew Taylor, Marshall (Sun Belt)", "Cl": "Sr.", "Ht": "6-3", "Pos": "G", "G": "32", "FGM": "253", "3FG": "83", "FT": "56", "PTS": "645", "PPG": "20.2"}, {"Rank": "26", "Player": "Denver Jones, FIU (C-USA)", "Cl": "So.", "Ht": "6-4", "Pos": "G", "G": "27", "FGM": "177", "3FG": "55", "FT": "130", "PTS": "539", "PPG": "20.0"}, {"Rank": "27", "Player": "Brandin Podziemski, Santa Clara (WCC)", "Cl": "So.", "Ht": "6-5", "Pos": "G", "G": "31", "FGM": "215", "3FG": "79", "FT": "109", "PTS": "618", "PPG": "19.9"}, {"Rank": "28", "Player": "Azuolas Tubelis, Arizona (Pac-12)", "Cl": "Jr.", "Ht": "6-11", "Pos": "F", "G": "31", "FGM": "243", "3FG": "9", "FT": "121", "PTS": "616", "PPG": "19.9"}, {"Rank": "29", "Player": "Jalen Wilson, Kansas (Big 12)", "Cl": "Jr.", "Ht": "6-8", "Pos": "F", "G": "31", "FGM": "208", "3FG": "61", "FT": "135", "PTS": "612", "PPG": "19.7"}, {"Rank": "30", "Player": "Noah Thomasson, Niagara (MAAC)", "Cl": "Sr.", "Ht": "6-3", "Pos": "G", "G": "29", "FGM": "219", "3FG": "48", "FT": "85", "PTS": "571", "PPG": "19.7"}, {"Rank": "31", "Player": "Jalen Moore, Oakland (Horizon)", "Cl": "Sr.", "Ht": "5-11", "Pos": "G", "G": "29", "FGM": "164", "3FG": "37", "FT": "204", "PTS": "569", "PPG": "19.6"}, {"Rank": "32", "Player": "Jordan Brown, Louisiana (Sun Belt)", "Cl": "Jr.", "Ht": "6-11", "Pos": "F", "G": "31", "FGM": "233", "3FG": "4", "FT": "138", "PTS": "608", "PPG": "19.6"}, {"Rank": "33", "Player": "Brandon Miller, Alabama (SEC)", "Cl": "Fr.", "Ht": "6-9", "Pos": "F", "G": "31", "FGM": "195", "3FG": "92", "FT": "125", "PTS": "607", "PPG": "19.6"}, {"Rank": "34", "Player": "Jamal Mashburn, Jr., New Mexico (Mountain West)", "Cl": "Jr.", "Ht": "6-2", "Pos": "G", "G": "31", "FGM": "215", "3FG": "44", "FT": "129", "PTS": "603", "PPG": "19.5"}, {"Rank": "35", "Player": "Ben Krikke, Valparaiso (MVC)", "Cl": "Sr.", "Ht": "6-9", "Pos": "F", "G": "32", "FGM": "244", "3FG": "17", "FT": "117", "PTS": "622", "PPG": "19.4"}, {"Rank": "36", "Player": "RayJ Dennis, Toledo (MAC)", "Cl": "Jr.", "Ht": "6-2", "Pos": "G", "G": "31", "FGM": "233", "3FG": "49", "FT": "87", "PTS": "602", "PPG": "19.4"}, {"Rank": "37", "Player": "Erik Reynolds II, Saint Joseph's (Atlantic 10)", "Cl": "So.", "Ht": "6-2", "Pos": "G", "G": "30", "FGM": "185", "3FG": "90", "FT": "122", "PTS": "582", "PPG": "19.4"}, {"Rank": "38", "Player": "Isaac Jones, Idaho (Big Sky)", "Cl": "Jr.", "Ht": "6-8", "Pos": "F", "G": "31", "FGM": "227", "3FG": "6", "FT": "140", "PTS": "600", "PPG": "19.4"}, {"Rank": "39", "Player": "Jr. Clay, Tennessee St. (OVC)", "Cl": "Jr.", "Ht": "6-0", "Pos": "G", "G": "30", "FGM": "196", "3FG": "63", "FT": "125", "PTS": "580", "PPG": "19.3"}, {"Rank": "40", "Player": "Quincy Olivari, Rice (C-USA)", "Cl": "Jr.", "Ht": "6-3", "Pos": "G", "G": "31", "FGM": "194", "3FG": "89", "FT": "122", "PTS": "599", "PPG": "19.3"}, {"Rank": "41", "Player": "Emoni Bates, Eastern Mich. (MAC)", "Cl": "So.", "Ht": "6-10", "Pos": "G", "G": "30", "FGM": "193", "3FG": "76", "FT": "115", "PTS": "577", "PPG": "19.2"}, {"Rank": "42", "Player": "Marques Warrick, Northern Ky. (Horizon)", "Cl": "Jr.", "Ht": "6-2", "Pos": "G", "G": "32", "FGM": "214", "3FG": "84", "FT": "98", "PTS": "610", "PPG": "19.1"}, {"Rank": "43", "Player": "Tucker DeVries, Drake (MVC)", "Cl": "So.", "Ht": "6-7", "Pos": "G", "G": "33", "FGM": "211", "3FG": "87", "FT": "119", "PTS": "628", "PPG": "19.0"}, {"Rank": "44", "Player": "Trenton Massner, Western Ill. (Summit League)", "Cl": "Sr.", "Ht": "6-3", "Pos": "G", "G": "29", "FGM": "194", "3FG": "85", "FT": "78", "PTS": "551", "PPG": "19.0"}, {"Rank": "45", "Player": "Ben Sheppard, Belmont (MVC)", "Cl": "Sr.", "Ht": "6-6", "Pos": "G", "G": "32", "FGM": "216", "3FG": "80", "FT": "91", "PTS": "603", "PPG": "18.8"}, {"Rank": "46", "Player": "Jaylen Forbes, Tulane (AAC)", "Cl": "Jr.", "Ht": "6-5", "Pos": "G", "G": "29", "FGM": "165", "3FG": "83", "FT": "133", "PTS": "546", "PPG": "18.8"}, {"Rank": "46", "Player": "Patrick Gardner, Marist (MAAC)", "Cl": "Sr.", "Ht": "6-11", "Pos": "C", "G": "29", "FGM": "210", "3FG": "48", "FT": "78", "PTS": "546", "PPG": "18.8"}, {"Rank": "48", "Player": "Chris Ledlum, Harvard (Ivy League)", "Cl": "Sr.", "Ht": "6-6", "Pos": "F", "G": "28", "FGM": "198", "3FG": "40", "FT": "91", "PTS": "527", "PPG": "18.8"}, {"Rank": "49", "Player": "Tyree Appleby, Wake Forest (ACC)", "Cl": "Sr.", "Ht": "6-0", "Pos": "G", "G": "31", "FGM": "174", "3FG": "71", "FT": "164", "PTS": "583", "PPG": "18.8"}, {"Rank": "50", "Player": "Demarcus Sharp, Northwestern St. (Southland)", "Cl": "Sr.", "Ht": "6-3", "Pos": "G", "G": "31", "FGM": "225", "3FG": "28", "FT": "103", "PTS": "581", "PPG": "18.7"}, {"Rank": "51", "Player": "Isaiah Burke, Morgan St. (MEAC)", "Cl": "Sr.", "Ht": "6-1", "Pos": "G", "G": "30", "FGM": "192", "3FG": "91", "FT": "87", "PTS": "562", "PPG": "18.7"}, {"Rank": "52", "Player": "Elijah Harkless, UNLV (Mountain West)", "Cl": "Sr.", "Ht": "6-3", "Pos": "G", "G": "30", "FGM": "177", "3FG": "47", "FT": "157", "PTS": "558", "PPG": "18.6"}, {"Rank": "53", "Player": "Tyler Burton, Richmond (Atlantic 10)", "Cl": "Sr.", "Ht": "6-7", "Pos": "F", "G": "31", "FGM": "191", "3FG": "53", "FT": "141", "PTS": "576", "PPG": "18.6"}, {"Rank": "54", "Player": "Isaiah Moore, South Alabama (Sun Belt)", "Cl": "Sr.", "Ht": "6-1", "Pos": "G", "G": "33", "FGM": "258", "3FG": "7", "FT": "86", "PTS": "609", "PPG": "18.5"}, {"Rank": "55", "Player": "Cameron Tyson, Seattle U (WAC)", "Cl": "Jr.", "Ht": "6-3", "Pos": "G", "G": "29", "FGM": "171", "3FG": "94", "FT": "96", "PTS": "532", "PPG": "18.3"}, {"Rank": "56", "Player": "Divant'e Moffitt, Idaho (Big Sky)", "Cl": "Sr.", "Ht": "6-3", "Pos": "G", "G": "32", "FGM": "209", "3FG": "20", "FT": "147", "PTS": "585", "PPG": "18.3"}, {"Rank": "57", "Player": "Hunter Dickinson, Michigan (Big Ten)", "Cl": "Jr.", "Ht": "7-1", "Pos": "C", "G": "31", "FGM": "219", "3FG": "22", "FT": "105", "PTS": "565", "PPG": "18.2"}, {"Rank": "58", "Player": "Zeke Mayo, South Dakota St. (Summit League)", "Cl": "So.", "Ht": "6-3", "Pos": "G", "G": "31", "FGM": "193", "3FG": "81", "FT": "97", "PTS": "564", "PPG": "18.2"}, {"Rank": "59", "Player": "Phillip Russell, Southeast Mo. St. (OVC)", "Cl": "So.", "Ht": "5-10", "Pos": "G", "G": "33", "FGM": "175", "3FG": "80", "FT": "170", "PTS": "600", "PPG": "18.2"}, {"Rank": "60", "Player": "Cameron Parker, Portland St. (Big Sky)", "Cl": "Sr.", "Ht": "6-2", "Pos": "G", "G": "29", "FGM": "155", "3FG": "21", "FT": "195", "PTS": "526", "PPG": "18.1"}, {"Rank": "61", "Player": "Boogie Ellis, Southern California (Pac-12)", "Cl": "Sr.", "Ht": "6-3", "Pos": "G", "G": "31", "FGM": "182", "3FG": "81", "FT": "117", "PTS": "562", "PPG": "18.1"}, {"Rank": "62", "Player": "Jordan Johnson, New Orleans (Southland)", "Cl": "Jr.", "Ht": "6-1", "Pos": "G", "G": "25", "FGM": "144", "3FG": "90", "FT": "75", "PTS": "453", "PPG": "18.1"}, {"Rank": "63", "Player": "Grant Nelson, North Dakota St. (Summit League)", "Cl": "Jr.", "Ht": "6-11", "Pos": "F", "G": "28", "FGM": "190", "3FG": "24", "FT": "103", "PTS": "507", "PPG": "18.1"}, {"Rank": "64", "Player": "Zyon Pullin, UC Riverside (Big West)", "Cl": "Sr.", "Ht": "6-4", "Pos": "G", "G": "27", "FGM": "183", "3FG": "25", "FT": "97", "PTS": "488", "PPG": "18.1"}, {"Rank": "65", "Player": "DaRon Holmes II, Dayton (Atlantic 10)", "Cl": "So.", "Ht": "6-10", "Pos": "F", "G": "31", "FGM": "209", "3FG": "5", "FT": "136", "PTS": "559", "PPG": "18.0"}, {"Rank": "65", "Player": "Jalen Pickett, Penn St. (Big Ten)", "Cl": "Sr.", "Ht": "6-4", "Pos": "G", "G": "31", "FGM": "227", "3FG": "42", "FT": "63", "PTS": "559", "PPG": "18.0"}, {"Rank": "67", "Player": "Mike Bothwell, Furman (SoCon)", "Cl": "Sr.", "Ht": "6-3", "Pos": "G", "G": "33", "FGM": "202", "3FG": "48", "FT": "143", "PTS": "595", "PPG": "18.0"}, {"Rank": "68", "Player": "Khalif Battle, Temple (AAC)", "Cl": "So.", "Ht": "6-5", "Pos": "G", "G": "27", "FGM": "155", "3FG": "77", "FT": "97", "PTS": "484", "PPG": "17.9"}, {"Rank": "69", "Player": "Isaiah Stevens, Colorado St. (Mountain West)", "Cl": "Sr.", "Ht": "6-0", "Pos": "G", "G": "24", "FGM": "159", "3FG": "44", "FT": "68", "PTS": "430", "PPG": "17.9"}, {"Rank": "70", "Player": "Bowen Born, UNI (MVC)", "Cl": "So.", "Ht": "5-11", "Pos": "G", "G": "32", "FGM": "177", "3FG": "80", "FT": "139", "PTS": "573", "PPG": "17.9"}, {"Rank": "71", "Player": "Tevian Jones, Southern Utah (WAC)", "Cl": "Sr.", "Ht": "6-7", "Pos": "G", "G": "30", "FGM": "156", "3FG": "72", "FT": "151", "PTS": "535", "PPG": "17.8"}, {"Rank": "72", "Player": "Keion Brooks Jr., Washington (Pac-12)", "Cl": "Sr.", "Ht": "6-7", "Pos": "F", "G": "29", "FGM": "180", "3FG": "31", "FT": "126", "PTS": "517", "PPG": "17.8"}, {"Rank": "73", "Player": "Dwayne Cohill, Youngstown St. (Horizon)", "Cl": "Sr.", "Ht": "6-2", "Pos": "G", "G": "32", "FGM": "198", "3FG": "50", "FT": "124", "PTS": "570", "PPG": "17.8"}, {"Rank": "74", "Player": "Jarred Godfrey, Purdue Fort Wayne (Horizon)", "Cl": "Sr.", "Ht": "6-5", "Pos": "G", "G": "31", "FGM": "173", "3FG": "71", "FT": "134", "PTS": "551", "PPG": "17.8"}, {"Rank": "74", "Player": "Keyontae Johnson, Kansas St. (Big 12)", "Cl": "Sr.", "Ht": "6-5", "Pos": "F", "G": "31", "FGM": "203", "3FG": "42", "FT": "103", "PTS": "551", "PPG": "17.8"}, {"Rank": "76", "Player": "Nicolas Timberlake, Towson (CAA)", "Cl": "Sr.", "Ht": "6-4", "Pos": "G", "G": "32", "FGM": "191", "3FG": "89", "FT": "96", "PTS": "567", "PPG": "17.7"}, {"Rank": "77", "Player": "El Ellis, Louisville (ACC)", "Cl": "Sr.", "Ht": "6-3", "Pos": "G", "G": "31", "FGM": "184", "3FG": "58", "FT": "123", "PTS": "549", "PPG": "17.7"}, {"Rank": "78", "Player": "Shaun Doss Jr., Ark.-Pine Bluff (SWAC)", "Cl": "Sr.", "Ht": "6-5", "Pos": "G", "G": "31", "FGM": "170", "3FG": "30", "FT": "178", "PTS": "548", "PPG": "17.7"}, {"Rank": "79", "Player": "Jacob Ognacevic, Lipscomb (ASUN)", "Cl": "So.", "Ht": "6-7", "Pos": "F", "G": "33", "FGM": "221", "3FG": "26", "FT": "115", "PTS": "583", "PPG": "17.7"}, {"Rank": "80", "Player": "Nate Calmese, Lamar University (Southland)", "Cl": "Fr.", "Ht": "6-2", "Pos": "G", "G": "31", "FGM": "203", "3FG": "61", "FT": "80", "PTS": "547", "PPG": "17.6"}, {"Rank": "81", "Player": "Khalil Shabazz, San Francisco (WCC)", "Cl": "Sr.", "Ht": "6-0", "Pos": "G", "G": "33", "FGM": "173", "3FG": "89", "FT": "144", "PTS": "579", "PPG": "17.5"}, {"Rank": "82", "Player": "Omari Moore, San Jose St. (Mountain West)", "Cl": "Jr.", "Ht": "6-6", "Pos": "G", "G": "31", "FGM": "197", "3FG": "60", "FT": "89", "PTS": "543", "PPG": "17.5"}, {"Rank": "83", "Player": "Brendan Adams, George Washington (Atlantic 10)", "Cl": "Sr.", "Ht": "6-4", "Pos": "G", "G": "31", "FGM": "183", "3FG": "73", "FT": "103", "PTS": "542", "PPG": "17.5"}, {"Rank": "83", "Player": "Jaime Jaquez Jr., UCLA (Pac-12)", "Cl": "Sr.", "Ht": "6-7", "Pos": "G", "G": "31", "FGM": "214", "3FG": "27", "FT": "87", "PTS": "542", "PPG": "17.5"}, {"Rank": "85", "Player": "Ray Harrison, Grand Canyon (WAC)", "Cl": "So.", "Ht": "6-4", "Pos": "G", "G": "31", "FGM": "173", "3FG": "41", "FT": "153", "PTS": "540", "PPG": "17.4"}, {"Rank": "85", "Player": "Mekhi Lairy, Miami (OH) (MAC)", "Cl": "Sr.", "Ht": "5-8", "Pos": "G", "G": "31", "FGM": "179", "3FG": "58", "FT": "124", "PTS": "540", "PPG": "17.4"}, {"Rank": "87", "Player": "KJ Williams, LSU (SEC)", "Cl": "Sr.", "Ht": "6-10", "Pos": "F", "G": "31", "FGM": "200", "3FG": "54", "FT": "85", "PTS": "539", "PPG": "17.4"}, {"Rank": "88", "Player": "BJ Freeman, Milwaukee (Horizon)", "Cl": "So.", "Ht": "6-6", "Pos": "G", "G": "29", "FGM": "166", "3FG": "69", "FT": "103", "PTS": "504", "PPG": "17.4"}, {"Rank": "89", "Player": "Claudell Harris Jr., Charleston So. (Big South)", "Cl": "So.", "Ht": "6-3", "Pos": "G", "G": "30", "FGM": "189", "3FG": "66", "FT": "77", "PTS": "521", "PPG": "17.4"}, {"Rank": "90", "Player": "Sincere Carry, Kent St. (MAC)", "Cl": "Sr.", "Ht": "6-1", "Pos": "G", "G": "31", "FGM": "187", "3FG": "55", "FT": "109", "PTS": "538", "PPG": "17.4"}, {"Rank": "90", "Player": "Jalen Cone, Northern Ariz. (Big Sky)", "Cl": "Jr.", "Ht": "5-11", "Pos": "G", "G": "31", "FGM": "176", "3FG": "89", "FT": "97", "PTS": "538", "PPG": "17.4"}, {"Rank": "92", "Player": "Zhuric Phelps, SMU (AAC)", "Cl": "So.", "Ht": "6-3", "Pos": "G", "G": "29", "FGM": "178", "3FG": "46", "FT": "101", "PTS": "503", "PPG": "17.3"}, {"Rank": "93", "Player": "Terquavion Smith, NC State (ACC)", "Cl": "So.", "Ht": "6-4", "Pos": "G", "G": "31", "FGM": "180", "3FG": "85", "FT": "92", "PTS": "537", "PPG": "17.3"}, {"Rank": "94", "Player": "Joe Bryant, Norfolk St. (MEAC)", "Cl": "Sr.", "Ht": "6-1", "Pos": "G", "G": "29", "FGM": "162", "3FG": "66", "FT": "112", "PTS": "502", "PPG": "17.3"}, {"Rank": "95", "Player": "Lamar Norman Jr., Western Mich. (MAC)", "Cl": "Sr.", "Ht": "6-1", "Pos": "G", "G": "30", "FGM": "176", "3FG": "85", "FT": "82", "PTS": "519", "PPG": "17.3"}, {"Rank": "96", "Player": "Kam  Woods, N.C. A&T (CAA)", "Cl": "So.", "Ht": "6-2", "Pos": "G", "G": "31", "FGM": "177", "3FG": "83", "FT": "99", "PTS": "536", "PPG": "17.3"}, {"Rank": "97", "Player": "RayQuawndis Mitchell, Kansas City (Summit League)", "Cl": "Sr.", "Ht": "6-5", "Pos": "G", "G": "32", "FGM": "161", "3FG": "79", "FT": "152", "PTS": "553", "PPG": "17.3"}, {"Rank": "98", "Player": "Marcellus Earlington, San Diego (WCC)", "Cl": "Sr.", "Ht": "6-6", "Pos": "F", "G": "30", "FGM": "181", "3FG": "37", "FT": "119", "PTS": "518", "PPG": "17.3"}, {"Rank": "98", "Player": "Jaden House, High Point (Big South)", "Cl": "Jr.", "Ht": "6-4", "Pos": "G", "G": "30", "FGM": "175", "3FG": "34", "FT": "134", "PTS": "518", "PPG": "17.3"}, {"Rank": "100", "Player": "Jarkel Joiner, NC State (ACC)", "Cl": "Sr.", "Ht": "6-1", "Pos": "G", "G": "31", "FGM": "184", "3FG": "58", "FT": "109", "PTS": "535", "PPG": "17.3"}, {"Rank": "101", "Player": "Daylen Kountz, Northern Colo. (Big Sky)", "Cl": "Sr.", "Ht": "6-4", "Pos": "G", "G": "32", "FGM": "187", "3FG": "33", "FT": "145", "PTS": "552", "PPG": "17.2"}, {"Rank": "102", "Player": "RaeQuan Battle, Montana St. (Big Sky)", "Cl": "Jr.", "Ht": "6-5", "Pos": "G", "G": "32", "FGM": "199", "3FG": "44", "FT": "108", "PTS": "550", "PPG": "17.2"}, {"Rank": "103", "Player": "Boo Buie, Northwestern (Big Ten)", "Cl": "Sr.", "Ht": "6-2", "Pos": "G", "G": "31", "FGM": "180", "3FG": "59", "FT": "113", "PTS": "532", "PPG": "17.2"}, {"Rank": "104", "Player": "Sherif Gross-Bullock, Bryant (America East)", "Cl": "Sr.", "Ht": "6-4", "Pos": "G", "G": "29", "FGM": "165", "3FG": "65", "FT": "102", "PTS": "497", "PPG": "17.1"}, {"Rank": "105", "Player": "Terrence Shannon Jr., Illinois (Big Ten)", "Cl": "Sr.", "Ht": "6-6", "Pos": "G", "G": "29", "FGM": "147", "3FG": "48", "FT": "153", "PTS": "495", "PPG": "17.1"}, {"Rank": "106", "Player": "Maxwell Lewis, Pepperdine (WCC)", "Cl": "So.", "Ht": "6-7", "Pos": "F", "G": "31", "FGM": "188", "3FG": "46", "FT": "107", "PTS": "529", "PPG": "17.1"}, {"Rank": "106", "Player": "Marcus Sasser, Houston (AAC)", "Cl": "Sr.", "Ht": "6-2", "Pos": "G", "G": "31", "FGM": "166", "3FG": "84", "FT": "113", "PTS": "529", "PPG": "17.1"}, {"Rank": "108", "Player": "Markquis Nowell, Kansas St. (Big 12)", "Cl": "Sr.", "Ht": "5-8", "Pos": "G", "G": "31", "FGM": "146", "3FG": "74", "FT": "162", "PTS": "528", "PPG": "17.0"}, {"Rank": "108", "Player": "DeAndre Williams, Memphis (AAC)", "Cl": "Sr.", "Ht": "6-9", "Pos": "F", "G": "31", "FGM": "205", "3FG": "21", "FT": "97", "PTS": "528", "PPG": "17.0"}, {"Rank": "110", "Player": "Darius Quisenberry, Fordham (Atlantic 10)", "Cl": "Sr.", "Ht": "6-2", "Pos": "G", "G": "30", "FGM": "149", "3FG": "68", "FT": "144", "PTS": "510", "PPG": "17.0"}, {"Rank": "110", "Player": "Shemarri Allen, Kansas City (Summit League)", "Cl": "Sr.", "Ht": "6-4", "Pos": "G", "G": "29", "FGM": "172", "3FG": "24", "FT": "125", "PTS": "493", "PPG": "17.0"}, {"Rank": "110", "Player": "Tylor Perry, North Texas (C-USA)", "Cl": "Sr.", "Ht": "5-11", "Pos": "G", "G": "29", "FGM": "138", "3FG": "89", "FT": "128", "PTS": "493", "PPG": "17.0"}, {"Rank": "113", "Player": "Atin Wright, CSUN (Big West)", "Cl": "So.", "Ht": "6-1", "Pos": "G", "G": "30", "FGM": "150", "3FG": "61", "FT": "148", "PTS": "509", "PPG": "17.0"}, {"Rank": "114", "Player": "Jarod Lucas, Nevada (Mountain West)", "Cl": "Sr.", "Ht": "6-4", "Pos": "G", "G": "31", "FGM": "153", "3FG": "76", "FT": "143", "PTS": "525", "PPG": "16.9"}, {"Rank": "115", "Player": "Adama Sanogo, UConn (Big East)", "Cl": "Jr.", "Ht": "6-9", "Pos": "F", "G": "31", "FGM": "214", "3FG": "17", "FT": "79", "PTS": "524", "PPG": "16.9"}, {"Rank": "116", "Player": "Camren Hunter, Central Ark. (ASUN)", "Cl": "So.", "Ht": "6-3", "Pos": "G", "G": "30", "FGM": "182", "3FG": "50", "FT": "92", "PTS": "506", "PPG": "16.9"}, {"Rank": "117", "Player": "Kino Lilly Jr., Brown (Ivy League)", "Cl": "So.", "Ht": "6-0", "Pos": "G", "G": "27", "FGM": "160", "3FG": "77", "FT": "58", "PTS": "455", "PPG": "16.9"}, {"Rank": "118", "Player": "Souley Boum, Xavier (Big East)", "Cl": "Sr.", "Ht": "6-3", "Pos": "G", "G": "31", "FGM": "163", "3FG": "68", "FT": "128", "PTS": "522", "PPG": "16.8"}, {"Rank": "119", "Player": "Jaelen House, New Mexico (Mountain West)", "Cl": "Sr.", "Ht": "6-0", "Pos": "G", "G": "29", "FGM": "151", "3FG": "51", "FT": "133", "PTS": "486", "PPG": "16.8"}, {"Rank": "120", "Player": "Demetre Roberts, FDU (NEC)", "Cl": "Sr.", "Ht": "5-8", "Pos": "G", "G": "33", "FGM": "180", "3FG": "59", "FT": "133", "PTS": "552", "PPG": "16.7"}, {"Rank": "121", "Player": "Joseph Girard III, Syracuse (ACC)", "Cl": "Sr.", "Ht": "6-1", "Pos": "G", "G": "31", "FGM": "175", "3FG": "86", "FT": "81", "PTS": "517", "PPG": "16.7"}, {"Rank": "121", "Player": "Caleb Love, North Carolina (ACC)", "Cl": "Jr.", "Ht": "6-4", "Pos": "G", "G": "31", "FGM": "176", "3FG": "68", "FT": "97", "PTS": "517", "PPG": "16.7"}, {"Rank": "123", "Player": "Marcus Domask, Southern Ill. (MVC)", "Cl": "Sr.", "Ht": "6-6", "Pos": "F", "G": "33", "FGM": "188", "3FG": "54", "FT": "120", "PTS": "550", "PPG": "16.7"}, {"Rank": "124", "Player": "Wesley Cardet, Chicago St. (DI Independent)", "Cl": "So.", "Ht": "6-6", "Pos": "G", "G": "31", "FGM": "164", "3FG": "32", "FT": "156", "PTS": "516", "PPG": "16.6"}, {"Rank": "125", "Player": "Jonathan Cisse, UIW (Southland)", "Cl": "Jr.", "Ht": "6-1", "Pos": "G", "G": "30", "FGM": "157", "3FG": "53", "FT": "132", "PTS": "499", "PPG": "16.6"}, {"Rank": "126", "Player": "Foster Loyer, Davidson (Atlantic 10)", "Cl": "Sr.", "Ht": "6-0", "Pos": "G", "G": "29", "FGM": "145", "3FG": "69", "FT": "123", "PTS": "482", "PPG": "16.6"}, {"Rank": "127", "Player": "Jalen Rucker, Army West Point (Patriot)", "Cl": "Jr.", "Ht": "5-10", "Pos": "G", "G": "33", "FGM": "204", "3FG": "50", "FT": "90", "PTS": "548", "PPG": "16.6"}, {"Rank": "128", "Player": "Ishmael Leggett, Rhode Island (Atlantic 10)", "Cl": "So.", "Ht": "6-2", "Pos": "G", "G": "30", "FGM": "153", "3FG": "47", "FT": "145", "PTS": "498", "PPG": "16.6"}, {"Rank": "129", "Player": "Tyler Harris, South Fla. (AAC)", "Cl": "Sr.", "Ht": "5-9", "Pos": "G", "G": "31", "FGM": "165", "3FG": "91", "FT": "93", "PTS": "514", "PPG": "16.6"}, {"Rank": "130", "Player": "Devontae Blanton, Eastern Ky. (ASUN)", "Cl": "Jr.", "Ht": "6-6", "Pos": "F", "G": "33", "FGM": "214", "3FG": "36", "FT": "83", "PTS": "547", "PPG": "16.6"}, {"Rank": "131", "Player": "Jace Carter, UIC (MVC)", "Cl": "So.", "Ht": "6-5", "Pos": "G", "G": "30", "FGM": "171", "3FG": "53", "FT": "102", "PTS": "497", "PPG": "16.6"}, {"Rank": "131", "Player": "Dillon Jones, Weber St. (Big Sky)", "Cl": "So.", "Ht": "6-6", "Pos": "F", "G": "30", "FGM": "158", "3FG": "35", "FT": "146", "PTS": "497", "PPG": "16.6"}, {"Rank": "133", "Player": "B.J. Mack, Wofford (SoCon)", "Cl": "Sr.", "Ht": "6-8", "Pos": "C", "G": "32", "FGM": "191", "3FG": "52", "FT": "96", "PTS": "530", "PPG": "16.6"}, {"Rank": "134", "Player": "Ricky Council IV, Arkansas (SEC)", "Cl": "Jr.", "Ht": "6-6", "Pos": "G", "G": "31", "FGM": "172", "3FG": "31", "FT": "138", "PTS": "513", "PPG": "16.5"}, {"Rank": "134", "Player": "Dayvion McKnight, Western Ky. (C-USA)", "Cl": "Jr.", "Ht": "6-1", "Pos": "G", "G": "31", "FGM": "185", "3FG": "18", "FT": "125", "PTS": "513", "PPG": "16.5"}, {"Rank": "136", "Player": "Walter Clayton Jr., Iona (MAAC)", "Cl": "So.", "Ht": "6-2", "Pos": "G", "G": "28", "FGM": "158", "3FG": "63", "FT": "84", "PTS": "463", "PPG": "16.5"}, {"Rank": "137", "Player": "Leon Ayers III, Bowling Green (MAC)", "Cl": "Sr.", "Ht": "6-5", "Pos": "G", "G": "31", "FGM": "187", "3FG": "41", "FT": "97", "PTS": "512", "PPG": "16.5"}, {"Rank": "137", "Player": "Landers Nolley II, Cincinnati (AAC)", "Cl": "Sr.", "Ht": "6-7", "Pos": "G", "G": "31", "FGM": "183", "3FG": "82", "FT": "64", "PTS": "512", "PPG": "16.5"}, {"Rank": "137", "Player": "Brice Sensabaugh, Ohio St. (Big Ten)", "Cl": "Fr.", "Ht": "6-6", "Pos": "F", "G": "31", "FGM": "185", "3FG": "59", "FT": "83", "PTS": "512", "PPG": "16.5"}, {"Rank": "137", "Player": "JT Shumate, Toledo (MAC)", "Cl": "Sr.", "Ht": "6-7", "Pos": "F", "G": "31", "FGM": "181", "3FG": "51", "FT": "99", "PTS": "512", "PPG": "16.5"}, {"Rank": "141", "Player": "Trey Townsend, Oakland (Horizon)", "Cl": "So.", "Ht": "6-6", "Pos": "F", "G": "32", "FGM": "212", "3FG": "20", "FT": "84", "PTS": "528", "PPG": "16.5"}, {"Rank": "141", "Player": "Armando Bacot, North Carolina (ACC)", "Cl": "Sr.", "Ht": "6-10", "Pos": "F", "G": "30", "FGM": "180", "3FG": "0", "FT": "135", "PTS": "495", "PPG": "16.5"}, {"Rank": "143", "Player": "Carter Hendricksen, North Florida (ASUN)", "Cl": "Sr.", "Ht": "6-7", "Pos": "F", "G": "31", "FGM": "168", "3FG": "72", "FT": "103", "PTS": "511", "PPG": "16.5"}, {"Rank": "144", "Player": "Grant Basile, Virginia Tech (ACC)", "Cl": "Sr.", "Ht": "6-9", "Pos": "F", "G": "31", "FGM": "196", "3FG": "62", "FT": "56", "PTS": "510", "PPG": "16.5"}, {"Rank": "144", "Player": "Enrique Freeman, Akron (MAC)", "Cl": "Jr.", "Ht": "6-7", "Pos": "F", "G": "31", "FGM": "201", "3FG": "1", "FT": "107", "PTS": "510", "PPG": "16.5"}, {"Rank": "146", "Player": "Morris Udeze, New Mexico (Mountain West)", "Cl": "Sr.", "Ht": "6-8", "Pos": "F", "G": "31", "FGM": "192", "3FG": "0", "FT": "125", "PTS": "509", "PPG": "16.4"}, {"Rank": "147", "Player": "Jordan Hawkins, UConn (Big East)", "Cl": "So.", "Ht": "6-5", "Pos": "G", "G": "29", "FGM": "146", "3FG": "84", "FT": "100", "PTS": "476", "PPG": "16.4"}, {"Rank": "148", "Player": "Oscar Tshiebwe, Kentucky (SEC)", "Cl": "Sr.", "Ht": "6-9", "Pos": "F", "G": "29", "FGM": "176", "3FG": "0", "FT": "123", "PTS": "475", "PPG": "16.4"}, {"Rank": "149", "Player": "Jahmyl Telfort, Northeastern (CAA)", "Cl": "Jr.", "Ht": "6-7", "Pos": "G", "G": "30", "FGM": "176", "3FG": "44", "FT": "95", "PTS": "491", "PPG": "16.4"}, {"Rank": "150", "Player": "Tyler Thomas, Hofstra (CAA)", "Cl": "Sr.", "Ht": "6-3", "Pos": "G", "G": "32", "FGM": "209", "3FG": "84", "FT": "21", "PTS": "523", "PPG": "16.3"}, {"Rank": "151", "Player": "Steven Ashworth, Utah St. (Mountain West)", "Cl": "Jr.", "Ht": "6-1", "Pos": "G", "G": "31", "FGM": "147", "3FG": "100", "FT": "112", "PTS": "506", "PPG": "16.3"}, {"Rank": "151", "Player": "Wade Taylor IV, Texas A&M (SEC)", "Cl": "So.", "Ht": "6-0", "Pos": "G", "G": "31", "FGM": "141", "3FG": "72", "FT": "152", "PTS": "506", "PPG": "16.3"}, {"Rank": "153", "Player": "Caleb Huffman, Nicholls (Southland)", "Cl": "Sr.", "Ht": "6-4", "Pos": "G", "G": "30", "FGM": "199", "3FG": "59", "FT": "32", "PTS": "489", "PPG": "16.3"}, {"Rank": "154", "Player": "Stephen Clark, The Citadel (SoCon)", "Cl": "Sr.", "Ht": "6-9", "Pos": "F", "G": "32", "FGM": "210", "3FG": "11", "FT": "90", "PTS": "521", "PPG": "16.3"}, {"Rank": "155", "Player": "Latrell Wrightsell Jr., Cal St. Fullerton (Big West)", "Cl": "Jr.", "Ht": "6-3", "Pos": "G", "G": "27", "FGM": "153", "3FG": "67", "FT": "66", "PTS": "439", "PPG": "16.3"}, {"Rank": "156", "Player": "Jahmir Young, Maryland (Big Ten)", "Cl": "Sr.", "Ht": "6-2", "Pos": "G", "G": "31", "FGM": "172", "3FG": "40", "FT": "120", "PTS": "504", "PPG": "16.3"}, {"Rank": "157", "Player": "Kelton Talford, Winthrop (Big South)", "Cl": "Jr.", "Ht": "6-7", "Pos": "F", "G": "30", "FGM": "184", "3FG": "0", "FT": "119", "PTS": "487", "PPG": "16.2"}, {"Rank": "158", "Player": "Marcus Carr, Texas (Big 12)", "Cl": "Sr.", "Ht": "6-2", "Pos": "G", "G": "31", "FGM": "172", "3FG": "70", "FT": "89", "PTS": "503", "PPG": "16.2"}, {"Rank": "158", "Player": "Judah Mintz, Syracuse (ACC)", "Cl": "Fr.", "Ht": "6-3", "Pos": "G", "G": "31", "FGM": "174", "3FG": "18", "FT": "137", "PTS": "503", "PPG": "16.2"}, {"Rank": "160", "Player": "Tyrell Roberts, San Francisco (WCC)", "Cl": "Sr.", "Ht": "5-11", "Pos": "G", "G": "33", "FGM": "183", "3FG": "84", "FT": "85", "PTS": "535", "PPG": "16.2"}, {"Rank": "161", "Player": "Kobe King, Valparaiso (MVC)", "Cl": "Jr.", "Ht": "6-4", "Pos": "G", "G": "32", "FGM": "195", "3FG": "19", "FT": "109", "PTS": "518", "PPG": "16.2"}, {"Rank": "162", "Player": "Gerrale Gates, Holy Cross (Patriot)", "Cl": "Sr.", "Ht": "6-6", "Pos": "F", "G": "31", "FGM": "204", "3FG": "1", "FT": "91", "PTS": "500", "PPG": "16.1"}, {"Rank": "162", "Player": "Grant Sherfield, Oklahoma (Big 12)", "Cl": "Sr.", "Ht": "6-2", "Pos": "G", "G": "31", "FGM": "167", "3FG": "81", "FT": "85", "PTS": "500", "PPG": "16.1"}, {"Rank": "164", "Player": "Parker Stewart, UT Martin (OVC)", "Cl": "Sr.", "Ht": "6-5", "Pos": "G", "G": "30", "FGM": "160", "3FG": "87", "FT": "76", "PTS": "483", "PPG": "16.1"}, {"Rank": "165", "Player": "Austin Crowley, Southern Miss. (Sun Belt)", "Cl": "Jr.", "Ht": "6-5", "Pos": "G", "G": "32", "FGM": "184", "3FG": "67", "FT": "80", "PTS": "515", "PPG": "16.1"}, {"Rank": "166", "Player": "Blake Hinson, Pittsburgh (ACC)", "Cl": "Jr.", "Ht": "6-7", "Pos": "F", "G": "31", "FGM": "163", "3FG": "88", "FT": "84", "PTS": "498", "PPG": "16.1"}, {"Rank": "166", "Player": "Bryce Hopkins, Providence (Big East)", "Cl": "So.", "Ht": "6-7", "Pos": "F", "G": "31", "FGM": "167", "3FG": "28", "FT": "136", "PTS": "498", "PPG": "16.1"}, {"Rank": "168", "Player": "Tre Jackson, Western Caro. (SoCon)", "Cl": "Jr.", "Ht": "6-0", "Pos": "G", "G": "32", "FGM": "165", "3FG": "111", "FT": "72", "PTS": "513", "PPG": "16.0"}, {"Rank": "169", "Player": "Branden Carlson, Utah (Pac-12)", "Cl": "Sr.", "Ht": "7-0", "Pos": "C", "G": "30", "FGM": "176", "3FG": "39", "FT": "89", "PTS": "480", "PPG": "16.0"}, {"Rank": "169", "Player": "Aanen Moody, Montana (Big Sky)", "Cl": "Sr.", "Ht": "6-3", "Pos": "G", "G": "25", "FGM": "127", "3FG": "66", "FT": "80", "PTS": "400", "PPG": "16.0"}, {"Rank": "171", "Player": "Keyonte George, Baylor (Big 12)", "Cl": "Fr.", "Ht": "6-4", "Pos": "G", "G": "30", "FGM": "149", "3FG": "73", "FT": "108", "PTS": "479", "PPG": "16.0"}, {"Rank": "172", "Player": "Justin Wright, N.C. Central (MEAC)", "Cl": "Jr.", "Ht": "6-2", "Pos": "G", "G": "28", "FGM": "157", "3FG": "32", "FT": "101", "PTS": "447", "PPG": "16.0"}, {"Rank": "173", "Player": "Colin Castleton, Florida (SEC)", "Cl": "Sr.", "Ht": "6-11", "Pos": "F", "G": "26", "FGM": "150", "3FG": "2", "FT": "113", "PTS": "415", "PPG": "16.0"}, {"Rank": "174", "Player": "Primo Spears, Georgetown (Big East)", "Cl": "So.", "Ht": "6-3", "Pos": "G", "G": "31", "FGM": "188", "3FG": "26", "FT": "92", "PTS": "494", "PPG": "15.9"}, {"Rank": "174", "Player": "Tristan da Silva, Colorado (Pac-12)", "Cl": "Jr.", "Ht": "6-9", "Pos": "F", "G": "31", "FGM": "188", "3FG": "47", "FT": "71", "PTS": "494", "PPG": "15.9"}, {"Rank": "176", "Player": "Isaiah Wong, Miami (FL) (ACC)", "Cl": "Jr.", "Ht": "6-4", "Pos": "G", "G": "30", "FGM": "153", "3FG": "51", "FT": "121", "PTS": "478", "PPG": "15.9"}, {"Rank": "177", "Player": "Marko Maletic, LIU (NEC)", "Cl": "So.", "Ht": "6-6", "Pos": "G", "G": "24", "FGM": "136", "3FG": "69", "FT": "41", "PTS": "382", "PPG": "15.9"}, {"Rank": "178", "Player": "Mason Harrell, Texas St. (Sun Belt)", "Cl": "Sr.", "Ht": "5-9", "Pos": "G", "G": "32", "FGM": "171", "3FG": "45", "FT": "122", "PTS": "509", "PPG": "15.9"}, {"Rank": "179", "Player": "Kobe Brown, Missouri (SEC)", "Cl": "Sr.", "Ht": "6-7", "Pos": "F", "G": "30", "FGM": "170", "3FG": "43", "FT": "94", "PTS": "477", "PPG": "15.9"}, {"Rank": "180", "Player": "Tommy Bruner, Denver (Summit League)", "Cl": "Jr.", "Ht": "6-1", "Pos": "G", "G": "32", "FGM": "157", "3FG": "48", "FT": "146", "PTS": "508", "PPG": "15.9"}, {"Rank": "181", "Player": "Setric Millner Jr., Toledo (MAC)", "Cl": "Sr.", "Ht": "6-7", "Pos": "F", "G": "31", "FGM": "177", "3FG": "51", "FT": "87", "PTS": "492", "PPG": "15.9"}, {"Rank": "182", "Player": "Dwight Wilson, Ohio (MAC)", "Cl": "Sr.", "Ht": "6-8", "Pos": "F", "G": "30", "FGM": "196", "3FG": "0", "FT": "84", "PTS": "476", "PPG": "15.9"}, {"Rank": "183", "Player": "KJ Simpson, Colorado (Pac-12)", "Cl": "So.", "Ht": "6-2", "Pos": "G", "G": "29", "FGM": "158", "3FG": "37", "FT": "107", "PTS": "460", "PPG": "15.9"}, {"Rank": "184", "Player": "Dwight Murray, Jr., Rider (MAAC)", "Cl": "Sr.", "Ht": "6-0", "Pos": "G", "G": "28", "FGM": "157", "3FG": "48", "FT": "82", "PTS": "444", "PPG": "15.9"}, {"Rank": "185", "Player": "Umoja Gibson, DePaul (Big East)", "Cl": "Sr.", "Ht": "6-1", "Pos": "G", "G": "31", "FGM": "156", "3FG": "84", "FT": "95", "PTS": "491", "PPG": "15.8"}, {"Rank": "186", "Player": "RJ Davis, North Carolina (ACC)", "Cl": "Jr.", "Ht": "6-0", "Pos": "G", "G": "31", "FGM": "164", "3FG": "55", "FT": "107", "PTS": "490", "PPG": "15.8"}, {"Rank": "187", "Player": "Trevian Tennyson, A&M-Corpus Christi (Southland)", "Cl": "Sr.", "Ht": "6-4", "Pos": "G", "G": "31", "FGM": "160", "3FG": "94", "FT": "75", "PTS": "489", "PPG": "15.8"}, {"Rank": "188", "Player": "Jalen Benjamin, Mount St. Mary's (MAAC)", "Cl": "Sr.", "Ht": "5-10", "Pos": "G", "G": "29", "FGM": "154", "3FG": "47", "FT": "102", "PTS": "457", "PPG": "15.8"}, {"Rank": "189", "Player": "Gerald Drumgoole Jr., UAlbany (America East)", "Cl": "Sr.", "Ht": "6-5", "Pos": "F", "G": "31", "FGM": "147", "3FG": "79", "FT": "115", "PTS": "488", "PPG": "15.7"}, {"Rank": "190", "Player": "Courvoisier McCauley, Indiana St. (MVC)", "Cl": "Sr.", "Ht": "6-5", "Pos": "G", "G": "33", "FGM": "182", "3FG": "101", "FT": "54", "PTS": "519", "PPG": "15.7"}, {"Rank": "191", "Player": "Eric Dixon, Villanova (Big East)", "Cl": "Sr.", "Ht": "6-8", "Pos": "F", "G": "31", "FGM": "177", "3FG": "37", "FT": "96", "PTS": "487", "PPG": "15.7"}, {"Rank": "192", "Player": "TJ Bamba, Washington St. (Pac-12)", "Cl": "Jr.", "Ht": "6-5", "Pos": "G", "G": "28", "FGM": "149", "3FG": "47", "FT": "94", "PTS": "439", "PPG": "15.7"}, {"Rank": "192", "Player": "David Coit, NIU (MAC)", "Cl": "So.", "Ht": "5-11", "Pos": "G", "G": "28", "FGM": "155", "3FG": "79", "FT": "50", "PTS": "439", "PPG": "15.7"}, {"Rank": "194", "Player": "Ajay Mitchell, UC Santa Barbara (Big West)", "Cl": "So.", "Ht": "6-4", "Pos": "G", "G": "31", "FGM": "167", "3FG": "18", "FT": "134", "PTS": "486", "PPG": "15.7"}, {"Rank": "194", "Player": "Hunter Tyson, Clemson (ACC)", "Cl": "Sr.", "Ht": "6-8", "Pos": "F", "G": "31", "FGM": "161", "3FG": "76", "FT": "88", "PTS": "486", "PPG": "15.7"}, {"Rank": "196", "Player": "Taylor Hendricks, UCF (AAC)", "Cl": "Fr.", "Ht": "6-9", "Pos": "F", "G": "30", "FGM": "165", "3FG": "57", "FT": "82", "PTS": "469", "PPG": "15.6"}, {"Rank": "197", "Player": "Tyler Robertson, Portland (WCC)", "Cl": "Jr.", "Ht": "6-6", "Pos": "G", "G": "32", "FGM": "147", "3FG": "43", "FT": "163", "PTS": "500", "PPG": "15.6"}, {"Rank": "198", "Player": "Josh Oduro, George Mason (Atlantic 10)", "Cl": "Sr.", "Ht": "6-9", "Pos": "F", "G": "31", "FGM": "191", "3FG": "7", "FT": "95", "PTS": "484", "PPG": "15.6"}, {"Rank": "199", "Player": "Adam Flagler, Baylor (Big 12)", "Cl": "Sr.", "Ht": "6-3", "Pos": "G", "G": "29", "FGM": "152", "3FG": "76", "FT": "72", "PTS": "452", "PPG": "15.6"}, {"Rank": "200", "Player": "Dawson Garcia, Minnesota (Big Ten)", "Cl": "So.", "Ht": "6-11", "Pos": "F", "G": "24", "FGM": "140", "3FG": "28", "FT": "66", "PTS": "374", "PPG": "15.6"}, {"Rank": "201", "Player": "Daryl Banks III, St. Bonaventure (Atlantic 10)", "Cl": "Jr.", "Ht": "6-3", "Pos": "G", "G": "31", "FGM": "140", "3FG": "79", "FT": "124", "PTS": "483", "PPG": "15.6"}, {"Rank": "202", "Player": "Javian McCollum, Siena (MAAC)", "Cl": "So.", "Ht": "6-2", "Pos": "G", "G": "26", "FGM": "129", "3FG": "48", "FT": "99", "PTS": "405", "PPG": "15.6"}, {"Rank": "203", "Player": "Jalen Slawson, Furman (SoCon)", "Cl": "Sr.", "Ht": "6-7", "Pos": "F", "G": "33", "FGM": "177", "3FG": "37", "FT": "123", "PTS": "514", "PPG": "15.6"}, {"Rank": "204", "Player": "Jordan King, ETSU (SoCon)", "Cl": "Sr.", "Ht": "6-0", "Pos": "G", "G": "32", "FGM": "174", "3FG": "69", "FT": "81", "PTS": "498", "PPG": "15.6"}, {"Rank": "205", "Player": "Jamarius Burton, Pittsburgh (ACC)", "Cl": "Sr.", "Ht": "6-4", "Pos": "G", "G": "29", "FGM": "173", "3FG": "18", "FT": "87", "PTS": "451", "PPG": "15.6"}, {"Rank": "206", "Player": "Erik Stevenson, West Virginia (Big 12)", "Cl": "Sr.", "Ht": "6-4", "Pos": "G", "G": "31", "FGM": "169", "3FG": "73", "FT": "71", "PTS": "482", "PPG": "15.5"}, {"Rank": "207", "Player": "Kahliel Spear, Robert Morris (Horizon)", "Cl": "Sr.", "Ht": "6-7", "Pos": "F", "G": "33", "FGM": "196", "3FG": "17", "FT": "103", "PTS": "512", "PPG": "15.5"}, {"Rank": "208", "Player": "Ja'Monta Black, Northwestern St. (Southland)", "Cl": "Jr.", "Ht": "6-3", "Pos": "G", "G": "30", "FGM": "143", "3FG": "115", "FT": "64", "PTS": "465", "PPG": "15.5"}, {"Rank": "208", "Player": "Sam Mennenga, Davidson (Atlantic 10)", "Cl": "Jr.", "Ht": "6-9", "Pos": "F", "G": "30", "FGM": "174", "3FG": "29", "FT": "88", "PTS": "465", "PPG": "15.5"}, {"Rank": "210", "Player": "Ray'Sean Taylor, SIUE (OVC)", "Cl": "So.", "Ht": "6-1", "Pos": "G", "G": "32", "FGM": "154", "3FG": "74", "FT": "113", "PTS": "495", "PPG": "15.5"}, {"Rank": "211", "Player": "PJ Hall, Clemson (ACC)", "Cl": "Jr.", "Ht": "6-10", "Pos": "F", "G": "30", "FGM": "177", "3FG": "30", "FT": "80", "PTS": "464", "PPG": "15.5"}, {"Rank": "212", "Player": "Jaylen Sebree, Tennessee Tech (OVC)", "Cl": "Sr.", "Ht": "6-7", "Pos": "F", "G": "33", "FGM": "179", "3FG": "62", "FT": "89", "PTS": "509", "PPG": "15.4"}, {"Rank": "213", "Player": "Enoch Cheeks, Robert Morris (Horizon)", "Cl": "Jr.", "Ht": "6-3", "Pos": "G", "G": "31", "FGM": "174", "3FG": "49", "FT": "81", "PTS": "478", "PPG": "15.4"}, {"Rank": "213", "Player": "Travis Evee, Rice (C-USA)", "Cl": "Jr.", "Ht": "6-1", "Pos": "G", "G": "31", "FGM": "154", "3FG": "72", "FT": "98", "PTS": "478", "PPG": "15.4"}, {"Rank": "213", "Player": "Sean Pedulla, Virginia Tech (ACC)", "Cl": "So.", "Ht": "6-1", "Pos": "G", "G": "31", "FGM": "167", "3FG": "63", "FT": "81", "PTS": "478", "PPG": "15.4"}, {"Rank": "216", "Player": "Clarence Daniels, New Hampshire (America East)", "Cl": "Jr.", "Ht": "6-6", "Pos": "F", "G": "29", "FGM": "161", "3FG": "30", "FT": "95", "PTS": "447", "PPG": "15.4"}, {"Rank": "217", "Player": "Nelly Joseph, Iona (MAAC)", "Cl": "Jr.", "Ht": "6-9", "Pos": "F", "G": "31", "FGM": "176", "3FG": "0", "FT": "125", "PTS": "477", "PPG": "15.4"}, {"Rank": "217", "Player": "Tolu Smith, Mississippi St. (SEC)", "Cl": "Sr.", "Ht": "6-11", "Pos": "F", "G": "31", "FGM": "176", "3FG": "0", "FT": "125", "PTS": "477", "PPG": "15.4"}, {"Rank": "219", "Player": "Dawson Baker, UC Irvine (Big West)", "Cl": "Jr.", "Ht": "6-3", "Pos": "G", "G": "32", "FGM": "173", "3FG": "45", "FT": "101", "PTS": "492", "PPG": "15.4"}, {"Rank": "219", "Player": "Tristan Enaruna, Cleveland St. (Horizon)", "Cl": "Jr.", "Ht": "6-8", "Pos": "F", "G": "32", "FGM": "192", "3FG": "9", "FT": "99", "PTS": "492", "PPG": "15.4"}, {"Rank": "221", "Player": "Tyzhaun Claude, Western Caro. (SoCon)", "Cl": "Jr.", "Ht": "6-8", "Pos": "F", "G": "30", "FGM": "167", "3FG": "2", "FT": "125", "PTS": "461", "PPG": "15.4"}, {"Rank": "221", "Player": "Damian Dunn, Temple (AAC)", "Cl": "So.", "Ht": "6-5", "Pos": "G", "G": "30", "FGM": "134", "3FG": "47", "FT": "146", "PTS": "461", "PPG": "15.4"}, {"Rank": "221", "Player": "Gedi Juozapaitis, Maine (America East)", "Cl": "Sr.", "Ht": "6-4", "Pos": "G", "G": "30", "FGM": "170", "3FG": "73", "FT": "48", "PTS": "461", "PPG": "15.4"}, {"Rank": "224", "Player": "Nico Galette, Sacred Heart (NEC)", "Cl": "Jr.", "Ht": "6-6", "Pos": "F", "G": "33", "FGM": "200", "3FG": "36", "FT": "71", "PTS": "507", "PPG": "15.4"}, {"Rank": "225", "Player": "Daniss Jenkins, Iona (MAAC)", "Cl": "Jr.", "Ht": "6-3", "Pos": "G", "G": "31", "FGM": "177", "3FG": "47", "FT": "75", "PTS": "476", "PPG": "15.4"}, {"Rank": "226", "Player": "Chris Harris, Southeast Mo. St. (OVC)", "Cl": "Sr.", "Ht": "6-3", "Pos": "G", "G": "34", "FGM": "149", "3FG": "60", "FT": "164", "PTS": "522", "PPG": "15.4"}, {"Rank": "227", "Player": "Colby Jones, Xavier (Big East)", "Cl": "Jr.", "Ht": "6-6", "Pos": "G", "G": "30", "FGM": "172", "3FG": "41", "FT": "75", "PTS": "460", "PPG": "15.3"}, {"Rank": "228", "Player": "Khalid Moore, Fordham (Atlantic 10)", "Cl": "Sr.", "Ht": "6-7", "Pos": "F", "G": "31", "FGM": "159", "3FG": "28", "FT": "129", "PTS": "475", "PPG": "15.3"}, {"Rank": "229", "Player": "Carlos Stewart, Santa Clara (WCC)", "Cl": "So.", "Ht": "6-1", "Pos": "G", "G": "32", "FGM": "170", "3FG": "56", "FT": "94", "PTS": "490", "PPG": "15.3"}, {"Rank": "229", "Player": "Steele Venters, Eastern Wash. (Big Sky)", "Cl": "So.", "Ht": "6-7", "Pos": "F", "G": "32", "FGM": "175", "3FG": "74", "FT": "66", "PTS": "490", "PPG": "15.3"}, {"Rank": "231", "Player": "Moses Wood, Portland (WCC)", "Cl": "Jr.", "Ht": "6-8", "Pos": "F", "G": "29", "FGM": "135", "3FG": "75", "FT": "99", "PTS": "444", "PPG": "15.3"}, {"Rank": "232", "Player": "Jyare Davis, Delaware (CAA)", "Cl": "So.", "Ht": "6-7", "Pos": "F", "G": "31", "FGM": "196", "3FG": "11", "FT": "71", "PTS": "474", "PPG": "15.3"}, {"Rank": "232", "Player": "Demaree King, Jacksonville St. (ASUN)", "Cl": "Sr.", "Ht": "6-0", "Pos": "G", "G": "31", "FGM": "165", "3FG": "103", "FT": "41", "PTS": "474", "PPG": "15.3"}, {"Rank": "232", "Player": "Julian Strawther, Gonzaga (WCC)", "Cl": "Jr.", "Ht": "6-7", "Pos": "G", "G": "31", "FGM": "161", "3FG": "69", "FT": "83", "PTS": "474", "PPG": "15.3"}, {"Rank": "235", "Player": "Jordan Sears, UT Martin (OVC)", "Cl": "So.", "Ht": "5-11", "Pos": "G", "G": "32", "FGM": "163", "3FG": "31", "FT": "132", "PTS": "489", "PPG": "15.3"}, {"Rank": "236", "Player": "Kam Jones, Marquette (Big East)", "Cl": "So.", "Ht": "6-4", "Pos": "G", "G": "31", "FGM": "176", "3FG": "87", "FT": "34", "PTS": "473", "PPG": "15.3"}, {"Rank": "237", "Player": "Felipe Haase, Southern Miss. (Sun Belt)", "Cl": "Sr.", "Ht": "6-9", "Pos": "F", "G": "32", "FGM": "158", "3FG": "60", "FT": "112", "PTS": "488", "PPG": "15.2"}, {"Rank": "238", "Player": "Morgan Safford, Miami (OH) (MAC)", "Cl": "Jr.", "Ht": "6-5", "Pos": "G", "G": "26", "FGM": "134", "3FG": "40", "FT": "88", "PTS": "396", "PPG": "15.2"}, {"Rank": "239", "Player": "DJ Davis, UC Irvine (Big West)", "Cl": "Jr.", "Ht": "6-0", "Pos": "G", "G": "31", "FGM": "149", "3FG": "77", "FT": "97", "PTS": "472", "PPG": "15.2"}, {"Rank": "239", "Player": "Joel Soriano, St. John's (NY) (Big East)", "Cl": "Sr.", "Ht": "6-11", "Pos": "F", "G": "31", "FGM": "178", "3FG": "0", "FT": "116", "PTS": "472", "PPG": "15.2"}, {"Rank": "241", "Player": "Austin Ash, The Citadel (SoCon)", "Cl": "Sr.", "Ht": "6-3", "Pos": "G", "G": "30", "FGM": "148", "3FG": "102", "FT": "58", "PTS": "456", "PPG": "15.2"}, {"Rank": "241", "Player": "Jalen Blackmon, Stetson (ASUN)", "Cl": "So.", "Ht": "6-3", "Pos": "G", "G": "30", "FGM": "153", "3FG": "69", "FT": "81", "PTS": "456", "PPG": "15.2"}, {"Rank": "243", "Player": "Sam Griffin, Tulsa (AAC)", "Cl": "Jr.", "Ht": "6-3", "Pos": "G", "G": "26", "FGM": "142", "3FG": "63", "FT": "48", "PTS": "395", "PPG": "15.2"}, {"Rank": "244", "Player": "Terry Collins, Mississippi Val. (SWAC)", "Cl": "Sr.", "Ht": "6-3", "Pos": "G", "G": "32", "FGM": "153", "3FG": "80", "FT": "100", "PTS": "486", "PPG": "15.2"}, {"Rank": "245", "Player": "Jalyn McCreary, Mercer (SoCon)", "Cl": "So.", "Ht": "0-0", "Pos": "F", "G": "33", "FGM": "228", "3FG": "0", "FT": "45", "PTS": "501", "PPG": "15.2"}, {"Rank": "246", "Player": "Dae Dae Grant, Duquesne (Atlantic 10)", "Cl": "Jr.", "Ht": "6-2", "Pos": "G", "G": "31", "FGM": "150", "3FG": "85", "FT": "85", "PTS": "470", "PPG": "15.2"}, {"Rank": "247", "Player": "Ant Nelson, Manhattan (MAAC)", "Cl": "Sr.", "Ht": "6-4", "Pos": "G", "G": "29", "FGM": "163", "3FG": "26", "FT": "87", "PTS": "439", "PPG": "15.1"}, {"Rank": "248", "Player": "Curtis Jones, Buffalo (MAC)", "Cl": "So.", "Ht": "6-5", "Pos": "G", "G": "30", "FGM": "164", "3FG": "73", "FT": "53", "PTS": "454", "PPG": "15.1"}, {"Rank": "248", "Player": "Jordan Miller, Miami (FL) (ACC)", "Cl": "Sr.", "Ht": "6-7", "Pos": "G", "G": "30", "FGM": "175", "3FG": "28", "FT": "76", "PTS": "454", "PPG": "15.1"}, {"Rank": "250", "Player": "Jordan Gainey, USC Upstate (Big South)", "Cl": "So.", "Ht": "6-4", "Pos": "G", "G": "31", "FGM": "160", "3FG": "69", "FT": "80", "PTS": "469", "PPG": "15.1"}, {"Rank": "250", "Player": "Gregory \"GG\" Jackson II, South Carolina (SEC)", "Cl": "Fr.", "Ht": "6-9", "Pos": "F", "G": "31", "FGM": "167", "3FG": "53", "FT": "82", "PTS": "469", "PPG": "15.1"}, {"Rank": "252", "Player": "David DeJulius, Cincinnati (AAC)", "Cl": "Sr.", "Ht": "6-0", "Pos": "G", "G": "31", "FGM": "169", "3FG": "56", "FT": "74", "PTS": "468", "PPG": "15.1"}, {"Rank": "253", "Player": "Ryan Kalkbrenner, Creighton (Big East)", "Cl": "Jr.", "Ht": "7-1", "Pos": "C", "G": "28", "FGM": "171", "3FG": "4", "FT": "76", "PTS": "422", "PPG": "15.1"}, {"Rank": "254", "Player": "Josh Bannan, Montana (Big Sky)", "Cl": "Jr.", "Ht": "6-10", "Pos": "F", "G": "29", "FGM": "162", "3FG": "19", "FT": "94", "PTS": "437", "PPG": "15.1"}, {"Rank": "255", "Player": "Jackson Paveletzke, Wofford (SoCon)", "Cl": "Fr.", "Ht": "6-3", "Pos": "G", "G": "33", "FGM": "167", "3FG": "46", "FT": "117", "PTS": "497", "PPG": "15.1"}, {"Rank": "256", "Player": "Eddy Kayouloud, Central Ark. (ASUN)", "Cl": "Sr.", "Ht": "6-7", "Pos": "F", "G": "31", "FGM": "187", "3FG": "36", "FT": "56", "PTS": "466", "PPG": "15.0"}, {"Rank": "257", "Player": "Tajion Jones, UNC Asheville (Big South)", "Cl": "Sr.", "Ht": "6-5", "Pos": "G", "G": "34", "FGM": "181", "3FG": "98", "FT": "50", "PTS": "510", "PPG": "15.0"}, {"Rank": "257", "Player": "Kyle Filipowski, Duke (ACC)", "Cl": "Fr.", "Ht": "7-0", "Pos": "C", "G": "31", "FGM": "157", "3FG": "29", "FT": "122", "PTS": "465", "PPG": "15.0"}, {"Rank": "257", "Player": "Mark Freeman, Morehead St. (OVC)", "Cl": "Sr.", "Ht": "5-10", "Pos": "G", "G": "28", "FGM": "134", "3FG": "50", "FT": "102", "PTS": "420", "PPG": "15.0"}, {"Rank": "257", "Player": "Liam Robbins, Vanderbilt (SEC)", "Cl": "Sr.", "Ht": "7-0", "Pos": "C", "G": "26", "FGM": "123", "3FG": "19", "FT": "125", "PTS": "390", "PPG": "15.0"}, {"Rank": "261", "Player": "Maks Klanjscek, Houston Christian (Southland)", "Cl": "Jr.", "Ht": "6-5", "Pos": "G", "G": "32", "FGM": "155", "3FG": "69", "FT": "100", "PTS": "479", "PPG": "15.0"}, {"Rank": "262", "Player": "Jase Townsend, San Diego (WCC)", "Cl": "Sr.", "Ht": "6-3", "Pos": "G", "G": "26", "FGM": "133", "3FG": "47", "FT": "76", "PTS": "389", "PPG": "15.0"}, {"Rank": "263", "Player": "Daniel Ortiz, North Ala. (ASUN)", "Cl": "So.", "Ht": "6-0", "Pos": "G", "G": "32", "FGM": "166", "3FG": "102", "FT": "44", "PTS": "478", "PPG": "14.9"}, {"Rank": "264", "Player": "Jordan Nesbitt, Hampton (CAA)", "Cl": "So.", "Ht": "6-6", "Pos": "G", "G": "32", "FGM": "157", "3FG": "44", "FT": "119", "PTS": "477", "PPG": "14.9"}, {"Rank": "264", "Player": "Isaiah Thompson, FGCU (ASUN)", "Cl": "Sr.", "Ht": "6-1", "Pos": "G", "G": "32", "FGM": "142", "3FG": "82", "FT": "111", "PTS": "477", "PPG": "14.9"}, {"Rank": "266", "Player": "Matthew Murrell, Ole Miss (SEC)", "Cl": "Jr.", "Ht": "6-4", "Pos": "G", "G": "28", "FGM": "134", "3FG": "60", "FT": "89", "PTS": "417", "PPG": "14.9"}, {"Rank": "267", "Player": "Paxson Wojcik, Brown (Ivy League)", "Cl": "Sr.", "Ht": "6-4", "Pos": "G", "G": "27", "FGM": "137", "3FG": "57", "FT": "71", "PTS": "402", "PPG": "14.9"}, {"Rank": "268", "Player": "Isaac Mushila, A&M-Corpus Christi (Southland)", "Cl": "Sr.", "Ht": "6-5", "Pos": "F", "G": "31", "FGM": "145", "3FG": "13", "FT": "158", "PTS": "461", "PPG": "14.9"}, {"Rank": "269", "Player": "Will Douglas, Prairie View (SWAC)", "Cl": "Sr.", "Ht": "6-5", "Pos": "G", "G": "30", "FGM": "157", "3FG": "30", "FT": "101", "PTS": "445", "PPG": "14.8"}, {"Rank": "270", "Player": "Hunter Maldonado, Wyoming (Mountain West)", "Cl": "Sr.", "Ht": "6-7", "Pos": "G", "G": "28", "FGM": "137", "3FG": "20", "FT": "121", "PTS": "415", "PPG": "14.8"}, {"Rank": "271", "Player": "Jake Heidbreder, Air Force (Mountain West)", "Cl": "So.", "Ht": "6-5", "Pos": "G", "G": "31", "FGM": "160", "3FG": "70", "FT": "69", "PTS": "459", "PPG": "14.8"}, {"Rank": "272", "Player": "KJ Simon, UT Martin (OVC)", "Cl": "Sr.", "Ht": "6-3", "Pos": "G", "G": "29", "FGM": "170", "3FG": "28", "FT": "61", "PTS": "429", "PPG": "14.8"}, {"Rank": "273", "Player": "Brycen Long, Houston Christian (Southland)", "Cl": "Jr.", "Ht": "6-2", "Pos": "G", "G": "32", "FGM": "141", "3FG": "94", "FT": "97", "PTS": "473", "PPG": "14.8"}, {"Rank": "274", "Player": "Walter Whyte, Boston U. (Patriot)", "Cl": "Sr.", "Ht": "6-6", "Pos": "F", "G": "31", "FGM": "162", "3FG": "48", "FT": "86", "PTS": "458", "PPG": "14.8"}, {"Rank": "275", "Player": "Ty Johnson, UC Davis (Big West)", "Cl": "So.", "Ht": "6-3", "Pos": "G", "G": "30", "FGM": "147", "3FG": "21", "FT": "128", "PTS": "443", "PPG": "14.8"}, {"Rank": "275", "Player": "Tyson Walker, Michigan St. (Big Ten)", "Cl": "Sr.", "Ht": "6-1", "Pos": "G", "G": "30", "FGM": "174", "3FG": "54", "FT": "41", "PTS": "443", "PPG": "14.8"}, {"Rank": "277", "Player": "Vonterius Woolbright, Western Caro. (SoCon)", "Cl": "Sr.", "Ht": "6-5", "Pos": "G", "G": "32", "FGM": "162", "3FG": "11", "FT": "137", "PTS": "472", "PPG": "14.8"}, {"Rank": "278", "Player": "Boden Skunberg, North Dakota St. (Summit League)", "Cl": "Jr.", "Ht": "6-5", "Pos": "G", "G": "30", "FGM": "153", "3FG": "52", "FT": "84", "PTS": "442", "PPG": "14.7"}, {"Rank": "279", "Player": "Logan Johnson, Saint Mary's (CA) (WCC)", "Cl": "Sr.", "Ht": "6-2", "Pos": "G", "G": "31", "FGM": "166", "3FG": "33", "FT": "90", "PTS": "455", "PPG": "14.7"}, {"Rank": "280", "Player": "Chris Youngblood, Kennesaw St. (ASUN)", "Cl": "Jr.", "Ht": "6-4", "Pos": "G", "G": "34", "FGM": "163", "3FG": "79", "FT": "94", "PTS": "499", "PPG": "14.7"}, {"Rank": "281", "Player": "Keith Higgins Jr., Lehigh (Patriot)", "Cl": "So.", "Ht": "6-4", "Pos": "G", "G": "30", "FGM": "157", "3FG": "63", "FT": "63", "PTS": "440", "PPG": "14.7"}, {"Rank": "282", "Player": "Frankie Fidler, Omaha (Summit League)", "Cl": "So.", "Ht": "6-7", "Pos": "F", "G": "32", "FGM": "152", "3FG": "24", "FT": "141", "PTS": "469", "PPG": "14.7"}, {"Rank": "283", "Player": "Caleb Daniels, Villanova (Big East)", "Cl": "Sr.", "Ht": "6-4", "Pos": "G", "G": "31", "FGM": "148", "3FG": "71", "FT": "87", "PTS": "454", "PPG": "14.6"}, {"Rank": "284", "Player": "LJ Cryer, Baylor (Big 12)", "Cl": "Jr.", "Ht": "6-1", "Pos": "G", "G": "28", "FGM": "141", "3FG": "72", "FT": "56", "PTS": "410", "PPG": "14.6"}, {"Rank": "285", "Player": "Latrell Jones, Nicholls (Southland)", "Cl": "Sr.", "Ht": "6-5", "Pos": "G", "G": "30", "FGM": "162", "3FG": "49", "FT": "66", "PTS": "439", "PPG": "14.6"}, {"Rank": "286", "Player": "Charles Pride, Bryant (America East)", "Cl": "Sr.", "Ht": "6-4", "Pos": "G", "G": "29", "FGM": "143", "3FG": "54", "FT": "84", "PTS": "424", "PPG": "14.6"}, {"Rank": "287", "Player": "Aidan Mahaney, Saint Mary's (CA) (WCC)", "Cl": "Fr.", "Ht": "6-3", "Pos": "G", "G": "31", "FGM": "169", "3FG": "70", "FT": "45", "PTS": "453", "PPG": "14.6"}, {"Rank": "288", "Player": "Kevin Cross, Tulane (AAC)", "Cl": "Jr.", "Ht": "6-8", "Pos": "F", "G": "28", "FGM": "151", "3FG": "12", "FT": "95", "PTS": "409", "PPG": "14.6"}, {"Rank": "289", "Player": "Jalen Haynes, ETSU (SoCon)", "Cl": "So.", "Ht": "6-8", "Pos": "F", "G": "32", "FGM": "176", "3FG": "3", "FT": "111", "PTS": "466", "PPG": "14.6"}, {"Rank": "290", "Player": "Jlynn Counter, IUPUI (Horizon)", "Cl": "So.", "Ht": "6-3", "Pos": "G", "G": "31", "FGM": "172", "3FG": "17", "FT": "90", "PTS": "451", "PPG": "14.5"}, {"Rank": "290", "Player": "Jesse Edwards, Syracuse (ACC)", "Cl": "Sr.", "Ht": "6-11", "Pos": "C", "G": "31", "FGM": "175", "3FG": "1", "FT": "100", "PTS": "451", "PPG": "14.5"}, {"Rank": "292", "Player": "Will Johnston, UTRGV (WAC)", "Cl": "So.", "Ht": "6-3", "Pos": "G", "G": "30", "FGM": "129", "3FG": "71", "FT": "107", "PTS": "436", "PPG": "14.5"}, {"Rank": "293", "Player": "Tosan Evbuomwan, Princeton (Ivy League)", "Cl": "Sr.", "Ht": "6-8", "Pos": "F", "G": "27", "FGM": "150", "3FG": "8", "FT": "84", "PTS": "392", "PPG": "14.5"}, {"Rank": "294", "Player": "Philip Alston, Loyola Chicago (Atlantic 10)", "Cl": "Jr.", "Ht": "6-6", "Pos": "F", "G": "30", "FGM": "149", "3FG": "27", "FT": "110", "PTS": "435", "PPG": "14.5"}, {"Rank": "294", "Player": "Jett Howard, Michigan (Big Ten)", "Cl": "Fr.", "Ht": "6-8", "Pos": "G", "G": "28", "FGM": "135", "3FG": "76", "FT": "60", "PTS": "406", "PPG": "14.5"}, {"Rank": "296", "Player": "Jarron Coleman, Ball St. (MAC)", "Cl": "Sr.", "Ht": "6-5", "Pos": "G", "G": "29", "FGM": "139", "3FG": "68", "FT": "74", "PTS": "420", "PPG": "14.5"}, {"Rank": "297", "Player": "Matt Knowling, Yale (Ivy League)", "Cl": "Jr.", "Ht": "6-6", "Pos": "F", "G": "21", "FGM": "136", "3FG": "3", "FT": "29", "PTS": "304", "PPG": "14.5"}, {"Rank": "298", "Player": "Mouhamed Gueye, Washington St. (Pac-12)", "Cl": "So.", "Ht": "6-11", "Pos": "F", "G": "31", "FGM": "176", "3FG": "10", "FT": "86", "PTS": "448", "PPG": "14.5"}, {"Rank": "299", "Player": "Marcus Tsohonis, Long Beach St. (Big West)", "Cl": "Jr.", "Ht": "6-3", "Pos": "G", "G": "27", "FGM": "143", "3FG": "28", "FT": "76", "PTS": "390", "PPG": "14.4"}, {"Rank": "300", "Player": "Briggs McClain, Hartford (DI Independent)", "Cl": "Jr.", "Ht": "6-4", "Pos": "G", "G": "25", "FGM": "139", "3FG": "39", "FT": "44", "PTS": "361", "PPG": "14.4"}, {"Rank": "301", "Player": "Tyreke Locure, ULM (Sun Belt)", "Cl": "Jr.", "Ht": "6-0", "Pos": "G", "G": "32", "FGM": "159", "3FG": "67", "FT": "77", "PTS": "462", "PPG": "14.4"}, {"Rank": "301", "Player": "Grant Singleton, FDU (NEC)", "Cl": "Sr.", "Ht": "5-9", "Pos": "G", "G": "32", "FGM": "164", "3FG": "72", "FT": "62", "PTS": "462", "PPG": "14.4"}, {"Rank": "303", "Player": "Kevin Obanor, Texas Tech (Big 12)", "Cl": "Sr.", "Ht": "6-8", "Pos": "F", "G": "31", "FGM": "149", "3FG": "39", "FT": "110", "PTS": "447", "PPG": "14.4"}, {"Rank": "304", "Player": "Max Rice, Boise St. (Mountain West)", "Cl": "Sr.", "Ht": "6-5", "Pos": "G", "G": "31", "FGM": "159", "3FG": "68", "FT": "60", "PTS": "446", "PPG": "14.4"}, {"Rank": "305", "Player": "Kinyon Hodges, Eastern Ill. (OVC)", "Cl": "Jr.", "Ht": "6-2", "Pos": "G", "G": "26", "FGM": "148", "3FG": "24", "FT": "54", "PTS": "374", "PPG": "14.4"}, {"Rank": "306", "Player": "Rob Perry, Murray St. (MVC)", "Cl": "Sr.", "Ht": "6-4", "Pos": "G", "G": "32", "FGM": "171", "3FG": "56", "FT": "62", "PTS": "460", "PPG": "14.4"}, {"Rank": "306", "Player": "Christian Shumate, McNeese (Southland)", "Cl": "So.", "Ht": "6-7", "Pos": "G", "G": "32", "FGM": "183", "3FG": "14", "FT": "80", "PTS": "460", "PPG": "14.4"}, {"Rank": "306", "Player": "Kenny Strawbridge, Evansville (MVC)", "Cl": "Sr.", "Ht": "6-6", "Pos": "G", "G": "32", "FGM": "168", "3FG": "30", "FT": "94", "PTS": "460", "PPG": "14.4"}, {"Rank": "309", "Player": "Kenan Blackshear, Nevada (Mountain West)", "Cl": "Sr.", "Ht": "6-6", "Pos": "G", "G": "31", "FGM": "151", "3FG": "17", "FT": "126", "PTS": "445", "PPG": "14.4"}, {"Rank": "309", "Player": "Le'Tre Darthard, Utah Valley (WAC)", "Cl": "Jr.", "Ht": "6-4", "Pos": "G", "G": "31", "FGM": "135", "3FG": "63", "FT": "112", "PTS": "445", "PPG": "14.4"}, {"Rank": "309", "Player": "Brian Taylor, Central Mich. (MAC)", "Cl": "Sr.", "Ht": "6-6", "Pos": "G", "G": "31", "FGM": "165", "3FG": "31", "FT": "84", "PTS": "445", "PPG": "14.4"}, {"Rank": "312", "Player": "Kris Bankston, Norfolk St. (MEAC)", "Cl": "Sr.", "Ht": "6-8", "Pos": "F", "G": "29", "FGM": "166", "3FG": "1", "FT": "83", "PTS": "416", "PPG": "14.3"}, {"Rank": "313", "Player": "Keyshaun Langley, UNC Greensboro (SoCon)", "Cl": "Sr.", "Ht": "6-1", "Pos": "G", "G": "32", "FGM": "161", "3FG": "90", "FT": "47", "PTS": "459", "PPG": "14.3"}, {"Rank": "314", "Player": "Tyler Stephenson-Moore, Stony Brook (CAA)", "Cl": "Sr.", "Ht": "6-3", "Pos": "G", "G": "30", "FGM": "152", "3FG": "48", "FT": "78", "PTS": "430", "PPG": "14.3"}, {"Rank": "314", "Player": "Kellen Tynes, Maine (America East)", "Cl": "So.", "Ht": "6-3", "Pos": "G", "G": "30", "FGM": "171", "3FG": "12", "FT": "76", "PTS": "430", "PPG": "14.3"}, {"Rank": "316", "Player": "Tyson Degenhart, Boise St. (Mountain West)", "Cl": "So.", "Ht": "6-7", "Pos": "F", "G": "31", "FGM": "175", "3FG": "35", "FT": "59", "PTS": "444", "PPG": "14.3"}, {"Rank": "316", "Player": "John Tonje, Colorado St. (Mountain West)", "Cl": "Sr.", "Ht": "6-5", "Pos": "G", "G": "31", "FGM": "145", "3FG": "57", "FT": "97", "PTS": "444", "PPG": "14.3"}, {"Rank": "318", "Player": "Brayon Freeman, Rhode Island (Atlantic 10)", "Cl": "So.", "Ht": "6-2", "Pos": "G", "G": "23", "FGM": "114", "3FG": "34", "FT": "67", "PTS": "329", "PPG": "14.3"}, {"Rank": "319", "Player": "Damarco Minor, SIUE (OVC)", "Cl": "So.", "Ht": "6-0", "Pos": "G", "G": "33", "FGM": "156", "3FG": "33", "FT": "127", "PTS": "472", "PPG": "14.3"}, {"Rank": "320", "Player": "Andrei Savrasov, Ga. Southern (Sun Belt)", "Cl": "Sr.", "Ht": "6-7", "Pos": "F", "G": "29", "FGM": "160", "3FG": "33", "FT": "61", "PTS": "414", "PPG": "14.3"}, {"Rank": "321", "Player": "Tyson Acuff, Eastern Mich. (MAC)", "Cl": "Jr.", "Ht": "6-4", "Pos": "G", "G": "30", "FGM": "151", "3FG": "52", "FT": "74", "PTS": "428", "PPG": "14.3"}, {"Rank": "321", "Player": "Kruz Perrott-Hunt, South Dakota (Summit League)", "Cl": "Sr.", "Ht": "6-3", "Pos": "G", "G": "30", "FGM": "152", "3FG": "58", "FT": "66", "PTS": "428", "PPG": "14.3"}, {"Rank": "323", "Player": "Gradey Dick, Kansas (Big 12)", "Cl": "Fr.", "Ht": "6-8", "Pos": "G", "G": "31", "FGM": "150", "3FG": "73", "FT": "69", "PTS": "442", "PPG": "14.3"}, {"Rank": "323", "Player": "D'Moi Hodge, Missouri (SEC)", "Cl": "Sr.", "Ht": "6-4", "Pos": "G", "G": "31", "FGM": "153", "3FG": "88", "FT": "48", "PTS": "442", "PPG": "14.3"}, {"Rank": "323", "Player": "Javan Johnson, DePaul (Big East)", "Cl": "Sr.", "Ht": "6-6", "Pos": "F", "G": "31", "FGM": "160", "3FG": "76", "FT": "46", "PTS": "442", "PPG": "14.3"}, {"Rank": "326", "Player": "Cameron Holden, Towson (CAA)", "Cl": "Sr.", "Ht": "6-5", "Pos": "F", "G": "29", "FGM": "146", "3FG": "17", "FT": "104", "PTS": "413", "PPG": "14.2"}, {"Rank": "327", "Player": "Anderson Mirambeaux, Miami (OH) (MAC)", "Cl": "Sr.", "Ht": "6-8", "Pos": "F", "G": "31", "FGM": "169", "3FG": "6", "FT": "97", "PTS": "441", "PPG": "14.2"}, {"Rank": "327", "Player": "Miles Norris, UC Santa Barbara (Big West)", "Cl": "Sr.", "Ht": "6-10", "Pos": "F", "G": "31", "FGM": "160", "3FG": "52", "FT": "69", "PTS": "441", "PPG": "14.2"}, {"Rank": "329", "Player": "Joey Hauser, Michigan St. (Big Ten)", "Cl": "Sr.", "Ht": "6-9", "Pos": "F", "G": "30", "FGM": "149", "3FG": "67", "FT": "61", "PTS": "426", "PPG": "14.2"}, {"Rank": "330", "Player": "Asher Woods, VMI (SoCon)", "Cl": "Fr.", "Ht": "6-3", "Pos": "G", "G": "32", "FGM": "160", "3FG": "49", "FT": "85", "PTS": "454", "PPG": "14.2"}, {"Rank": "331", "Player": "Ricky Clemons, Campbell (Big South)", "Cl": "Sr.", "Ht": "6-2", "Pos": "G", "G": "34", "FGM": "150", "3FG": "27", "FT": "155", "PTS": "482", "PPG": "14.2"}, {"Rank": "332", "Player": "Evan Taylor, Lehigh (Patriot)", "Cl": "Sr.", "Ht": "6-6", "Pos": "G", "G": "30", "FGM": "151", "3FG": "55", "FT": "68", "PTS": "425", "PPG": "14.2"}, {"Rank": "333", "Player": "Jahsean Corbett, Chicago St. (DI Independent)", "Cl": "So.", "Ht": "6-6", "Pos": "G", "G": "31", "FGM": "173", "3FG": "34", "FT": "59", "PTS": "439", "PPG": "14.2"}, {"Rank": "333", "Player": "Miles Kelly, Georgia Tech (ACC)", "Cl": "So.", "Ht": "6-6", "Pos": "G", "G": "31", "FGM": "155", "3FG": "82", "FT": "47", "PTS": "439", "PPG": "14.2"}, {"Rank": "333", "Player": "Skyelar Potter, Jacksonville St. (ASUN)", "Cl": "Sr.", "Ht": "6-3", "Pos": "G", "G": "31", "FGM": "142", "3FG": "76", "FT": "79", "PTS": "439", "PPG": "14.2"}, {"Rank": "333", "Player": "Antonio Reeves, Kentucky (SEC)", "Cl": "Sr.", "Ht": "6-6", "Pos": "G", "G": "31", "FGM": "151", "3FG": "71", "FT": "66", "PTS": "439", "PPG": "14.2"}, {"Rank": "337", "Player": "Brandon Rush, Youngstown St. (Horizon)", "Cl": "Jr.", "Ht": "6-3", "Pos": "G", "G": "32", "FGM": "166", "3FG": "73", "FT": "48", "PTS": "453", "PPG": "14.2"}, {"Rank": "337", "Player": "Marcus Watson, N.C. A&T (CAA)", "Cl": "Jr.", "Ht": "6-6", "Pos": "G", "G": "32", "FGM": "165", "3FG": "44", "FT": "79", "PTS": "453", "PPG": "14.2"}, {"Rank": "339", "Player": "Boogie Anderson, Southeastern La. (Southland)", "Cl": "Sr.", "Ht": "6-4", "Pos": "G", "G": "30", "FGM": "180", "3FG": "0", "FT": "64", "PTS": "424", "PPG": "14.1"}, {"Rank": "340", "Player": "Drew Peterson, Southern California (Pac-12)", "Cl": "Sr.", "Ht": "6-9", "Pos": "G", "G": "31", "FGM": "158", "3FG": "45", "FT": "77", "PTS": "438", "PPG": "14.1"}, {"Rank": "341", "Player": "Xander Rice, Bucknell (Patriot)", "Cl": "Sr.", "Ht": "6-3", "Pos": "G", "G": "32", "FGM": "153", "3FG": "69", "FT": "77", "PTS": "452", "PPG": "14.1"}, {"Rank": "341", "Player": "Matt Rogers, American (Patriot)", "Cl": "Jr.", "Ht": "6-9", "Pos": "F", "G": "32", "FGM": "182", "3FG": "20", "FT": "68", "PTS": "452", "PPG": "14.1"}, {"Rank": "343", "Player": "Zach Austin, High Point (Big South)", "Cl": "So.", "Ht": "6-7", "Pos": "F", "G": "31", "FGM": "149", "3FG": "62", "FT": "77", "PTS": "437", "PPG": "14.1"}, {"Rank": "344", "Player": "Ansley Almonor, FDU (NEC)", "Cl": "So.", "Ht": "6-6", "Pos": "F", "G": "32", "FGM": "163", "3FG": "67", "FT": "58", "PTS": "451", "PPG": "14.1"}, {"Rank": "344", "Player": "Kellen Amos, Central Conn. St. (NEC)", "Cl": "Jr.", "Ht": "6-6", "Pos": "G", "G": "32", "FGM": "173", "3FG": "63", "FT": "42", "PTS": "451", "PPG": "14.1"}, {"Rank": "346", "Player": "Norchad Omier, Miami (FL) (ACC)", "Cl": "So.", "Ht": "6-7", "Pos": "F", "G": "30", "FGM": "164", "3FG": "5", "FT": "89", "PTS": "422", "PPG": "14.1"}, {"Rank": "347", "Player": "Chase Audige, Northwestern (Big Ten)", "Cl": "Sr.", "Ht": "6-4", "Pos": "G", "G": "31", "FGM": "152", "3FG": "62", "FT": "70", "PTS": "436", "PPG": "14.1"}, {"Rank": "348", "Player": "Jaykwon Walton, Wichita St. (AAC)", "Cl": "Jr.", "Ht": "6-7", "Pos": "G", "G": "26", "FGM": "127", "3FG": "36", "FT": "75", "PTS": "365", "PPG": "14.0"}, {"Rank": "349", "Player": "Chase Hunter, Clemson (ACC)", "Cl": "Jr.", "Ht": "6-3", "Pos": "G", "G": "28", "FGM": "131", "3FG": "46", "FT": "85", "PTS": "393", "PPG": "14.0"}, {"Rank": "350", "Player": "Khalil Brantley, La Salle (Atlantic 10)", "Cl": "So.", "Ht": "6-1", "Pos": "G", "G": "29", "FGM": "138", "3FG": "32", "FT": "99", "PTS": "407", "PPG": "14.0"}, {"Rank": "350", "Player": "Matthew Cleveland, Florida St. (ACC)", "Cl": "So.", "Ht": "6-7", "Pos": "G", "G": "29", "FGM": "154", "3FG": "20", "FT": "79", "PTS": "407", "PPG": "14.0"}]